learning_pipeline_plugin/__init__.py
learning_pipeline_plugin/actfw_utils/__init__.py
learning_pipeline_plugin/actfw_utils/isolated_task.py
learning_pipeline_plugin/actfw_utils/pseudo_pipe.py
learning_pipeline_plugin/algorithms/__init__.py
learning_pipeline_plugin/algorithms/stream_al.py
learning_pipeline_plugin/algorithms/submodular_diversity.py
learning_pipeline_plugin/algorithms/submodular_utils.py
learning_pipeline_plugin/algorithms/type_helper.py
learning_pipeline_plugin/algorithms/uncertainty.py
learning_pipeline_plugin/collect_pipe.py
learning_pipeline_plugin/notifier.py
learning_pipeline_plugin/select_task.py
learning_pipeline_plugin/sender_task.py
learning_pipeline_plugin-0.6.0.dist-info/METADATA
learning_pipeline_plugin-0.6.0.dist-info/WHEEL
learning_pipeline_plugin-0.6.0.dist-info/RECORD
