Metadata-Version: 2.1
Name: learning-pipeline-plugin
Version: 0.6.0
Summary: 
Home-page: https://github.com/Idein/learning-pipeline-plugin
License: MIT
Author: Idein Inc.
Requires-Python: >=3.7.0,<3.11
Classifier: License :: OSI Approved :: MIT License
Classifier: Programming Language :: Python :: 3
Classifier: Programming Language :: Python :: 3.7
Classifier: Programming Language :: Python :: 3.8
Classifier: Programming Language :: Python :: 3.9
Classifier: Programming Language :: Python :: 3.10
Requires-Dist: actfw-core (>=2.2.0,<3.0.0)
Requires-Dist: numpy (>=1,<2)
Requires-Dist: pillow (>=5,<6) ; python_version < "3.8"
Requires-Dist: pillow (>=8,<9) ; python_version >= "3.8"
Requires-Dist: requests[socks] (>=2.28.1,<3.0.0)
Requires-Dist: typing-extensions (>=4.4.0,<5.0.0)
Project-URL: Repository, https://github.com/Idein/learning-pipeline-plugin
